ip2asn/__init__.py
ip2asn/main.py
ip2asn/test.py
ip2asn/tests/test_big_numbers_converter.py
ip2asn/tests/test_ip2asn.py
ip2asn-1.6.6.dist-info/METADATA
ip2asn-1.6.6.dist-info/WHEEL
ip2asn-1.6.6.dist-info/entry_points.txt
ip2asn-1.6.6.dist-info/licenses/LICENSE.txt
ip2asn-1.6.6.dist-info/RECORD
