Metadata-Version: 2.3
Name: ip2asn
Version: 1.6.6
Summary: Quickly look up ownership information about IP addresses
Project-URL: Homepage, https://github.com/hardaker/ip2asn
Author-email: Wes Hardaker <opensource@hardakers.net>
License: MIT License
Classifier: License :: OSI Approved :: MIT License
Classifier: Operating System :: OS Independent
Classifier: Programming Language :: Python :: 3
Requires-Python: >=3.7
Requires-Dist: msgpack
Requires-Dist: pyfsdb
Requires-Dist: requests
